sapiens_embedding/__init__.py
sapiens_embedding/sapiens_embedding.py
sapiens_embedding-1.1.1.dist-info/LICENSE.txt
sapiens_embedding-1.1.1.dist-info/METADATA
sapiens_embedding-1.1.1.dist-info/WHEEL
sapiens_embedding-1.1.1.dist-info/top_level.txt
sapiens_embedding-1.1.1.dist-info/RECORD
