Metadata-Version: 2.2
Name: sapiens_embedding
Version: 1.1.1
Home-page: https://github.com/sapiens-technology/SapiensEmbedding
Author: SAPIENS TECHNOLOGY
License: Proprietary Software
License-File: LICENSE.txt
Requires-Dist: sapiens-tokenizer
Dynamic: author
Dynamic: home-page
Dynamic: license
Dynamic: requires-dist
